xt_nlp/__init__.py
xt_nlp/metrics.py
xt_nlp/utils/__init__.py
xt_nlp/utils/datasets.py
xt_nlp/utils/helpers.py
xt_nlp/utils/infer.py
xt_nlp/utils/postprocessing.py
xt_nlp/utils/preprocessing.py
xt_nlp/utils/ses_utils.py
xt_nlp/utils/statistics.py
xt_nlp-0.2.7.dist-info/METADATA
xt_nlp-0.2.7.dist-info/WHEEL
xt_nlp-0.2.7.dist-info/top_level.txt
xt_nlp-0.2.7.dist-info/RECORD
