Metadata-Version: 2.1
Name: xt-nlp
Version: 0.2.7
Summary: Utilities for training and working with nlp models in pytorch
Home-page: https://github.com/XtractTech/xt-nlp
Author: Xtract AI
Author-email: info@xtract.ai
License: UNKNOWN
Platform: UNKNOWN
Classifier: Programming Language :: Python :: 3
Classifier: Operating System :: OS Independent
Provides: xt_nlp
Requires-Dist: transformers
Requires-Dist: numpy
Requires-Dist: torch
Requires-Dist: scikit-learn
Requires-Dist: xt-training
